pyleaflet/__init__.py
pyleaflet/exceptions.py
pyleaflet/map.py
pyleaflet/tilelayer.py
pyleaflet-0.1.1.dist-info/LICENSE.md
pyleaflet-0.1.1.dist-info/METADATA
pyleaflet-0.1.1.dist-info/WHEEL
pyleaflet-0.1.1.dist-info/top_level.txt
pyleaflet-0.1.1.dist-info/RECORD
